idlemypyextension/__init__.py
idlemypyextension/annotate.py
idlemypyextension/client.py
idlemypyextension/extension.py
idlemypyextension/moduleguard.py
idlemypyextension/py.typed
idlemypyextension/tktrio.py
idlemypyextension/utils.py
idlemypyextension-1.4.0.dist-info/licenses/LICENSE
idlemypyextension-1.4.0.dist-info/METADATA
idlemypyextension-1.4.0.dist-info/WHEEL
idlemypyextension-1.4.0.dist-info/entry_points.txt
idlemypyextension-1.4.0.dist-info/top_level.txt
idlemypyextension-1.4.0.dist-info/RECORD
