Metadata-Version: 2.4
Name: idlemypyextension
Version: 1.4.0
Summary: Mypy daemon extension for Python IDLE
Author-email: CoolCat467 <CoolCat467@duck.com>
License:                     GNU GENERAL PUBLIC LICENSE
Project-URL: Source, https://github.com/CoolCat467/idlemypyextension
Project-URL: Bug Tracker, https://github.com/CoolCat467/idlemypyextension/issues
Keywords: mypy,dmypy,idle,extension,development,daemon
Classifier: Development Status :: 4 - Beta
Classifier: Intended Audience :: Developers
Classifier: License :: OSI Approved :: GNU General Public License v3 (GPLv3)
Classifier: Natural Language :: English
Classifier: Programming Language :: Python :: 3
Classifier: Programming Language :: Python :: 3.10
Classifier: Programming Language :: Python :: 3.11
Classifier: Programming Language :: Python :: 3.12
Classifier: Programming Language :: Python :: 3.13
Classifier: Programming Language :: Python :: 3 :: Only
Classifier: Topic :: Software Development
Classifier: Topic :: Text Editors :: Integrated Development Environments (IDE)
Classifier: Topic :: Utilities
Classifier: Operating System :: OS Independent
Classifier: Framework :: IDLE
Classifier: Framework :: Trio
Classifier: Typing :: Typed
Requires-Python: >=3.10
License-File: LICENSE
Requires-Dist: mypy[dmypy]>=1.17.0
Requires-Dist: orjson>=3.10.18
Requires-Dist: trio>=0.30.0
Provides-Extra: user
Requires-Dist: idleuserextend~=0.0.3; extra == "user"
Provides-Extra: tests
Requires-Dist: pytest>=5.0; extra == "tests"
Requires-Dist: pytest-cov>=6.0.0; extra == "tests"
Requires-Dist: pytest-trio>=0.8.0; extra == "tests"
Requires-Dist: coverage>=7.2.5; extra == "tests"
Requires-Dist: uv>=0.5.21; extra == "tests"
Provides-Extra: tools
Requires-Dist: ruff>=0.9.2; extra == "tools"
Requires-Dist: codespell>=2.3.0; extra == "tools"
Requires-Dist: pre-commit>=4.2.0; extra == "tools"
Requires-Dist: attrs>=25.3.0; extra == "tools"
Requires-Dist: types-idlelib>=0.0.0; extra == "tools"
Dynamic: license-file
